uhttp_multipart.py
uhttp_multipart-0.2.0.dist-info/LICENSE
uhttp_multipart-0.2.0.dist-info/METADATA
uhttp_multipart-0.2.0.dist-info/WHEEL
uhttp_multipart-0.2.0.dist-info/RECORD
